tesseract_core/__init__.py
tesseract_core/_version.py
tesseract_core/runtime/__init__.py
tesseract_core/runtime/app_cli.py
tesseract_core/runtime/app_http.py
tesseract_core/runtime/array_encoding.py
tesseract_core/runtime/cli.py
tesseract_core/runtime/config.py
tesseract_core/runtime/core.py
tesseract_core/runtime/experimental.py
tesseract_core/runtime/file_interactions.py
tesseract_core/runtime/finite_differences.py
tesseract_core/runtime/logs.py
tesseract_core/runtime/mpa.py
tesseract_core/runtime/schema_generation.py
tesseract_core/runtime/schema_types.py
tesseract_core/runtime/serve.py
tesseract_core/runtime/tree_transforms.py
tesseract_core/runtime/meta/.dockerignore
tesseract_core/runtime/meta/README.md
tesseract_core/runtime/meta/pyproject.toml
tesseract_core/runtime/meta/requirements.txt
tesseract_core/sdk/__init__.py
tesseract_core/sdk/api_parse.py
tesseract_core/sdk/cli.py
tesseract_core/sdk/config.py
tesseract_core/sdk/docker_client.py
tesseract_core/sdk/engine.py
tesseract_core/sdk/exceptions.py
tesseract_core/sdk/logs.py
tesseract_core/sdk/tesseract.py
tesseract_core/sdk/templates/Dockerfile.base
tesseract_core/sdk/templates/addmeplease.c
tesseract_core/sdk/templates/build_conda_venv.sh
tesseract_core/sdk/templates/build_pip_venv.sh
tesseract_core/sdk/templates/entrypoint.sh
tesseract_core/sdk/templates/base/tesseract_api.py
tesseract_core/sdk/templates/base/tesseract_config.yaml
tesseract_core/sdk/templates/base/tesseract_requirements.txt
tesseract_core/sdk/templates/jax/tesseract_api.py
tesseract_core/sdk/templates/jax/tesseract_config.yaml
tesseract_core/sdk/templates/jax/tesseract_requirements.txt
tesseract_core/sdk/templates/pytorch/tesseract_api.py
tesseract_core/sdk/templates/pytorch/tesseract_config.yaml
tesseract_core/sdk/templates/pytorch/tesseract_requirements.txt
tesseract_core-1.3.0.dist-info/METADATA
tesseract_core-1.3.0.dist-info/WHEEL
tesseract_core-1.3.0.dist-info/entry_points.txt
tesseract_core-1.3.0.dist-info/licenses/LICENSE
tesseract_core-1.3.0.dist-info/RECORD
