Metadata-Version: 2.4
Name: tesseract-core
Version: 1.3.0
Summary: A toolkit for universal, autodiff-native software components.
Project-URL: Homepage, https://github.com/pasteurlabs/tesseract-core
Project-URL: Documentation, https://docs.pasteurlabs.ai/projects/tesseract-core/latest
Author-email: "The Tesseract team @ Pasteur Labs + OSS contributors" <info@simulation.science>
License: Apache-2.0
License-File: LICENSE
Requires-Python: <3.14,>=3.10
Requires-Dist: jinja2
Requires-Dist: numpy
Requires-Dist: pip
Requires-Dist: pydantic
Requires-Dist: pyyaml
Requires-Dist: requests>=2.32.4
Requires-Dist: rich
Requires-Dist: typer
Provides-Extra: dev
Requires-Dist: aiobotocore>=2.19.0; extra == 'dev'
Requires-Dist: autodoc-pydantic; extra == 'dev'
Requires-Dist: click<=8.3.1,>=8.1; extra == 'dev'
Requires-Dist: debugpy<=1.8.19,>=1.8.14; extra == 'dev'
Requires-Dist: docker; extra == 'dev'
Requires-Dist: fastapi; extra == 'dev'
Requires-Dist: fastapi<=0.128.0,>=0.115; extra == 'dev'
Requires-Dist: fsspec[http,s3]<=2025.12.0,>=2024.12; extra == 'dev'
Requires-Dist: furo; extra == 'dev'
Requires-Dist: httpx; extra == 'dev'
Requires-Dist: jsf; extra == 'dev'
Requires-Dist: mlflow-skinny<=3.8.1,>=3.7.0; extra == 'dev'
Requires-Dist: moto[server]; extra == 'dev'
Requires-Dist: myst-nb; extra == 'dev'
Requires-Dist: numpy; extra == 'dev'
Requires-Dist: numpy<=2.4.0,>=1.26; extra == 'dev'
Requires-Dist: pre-commit; extra == 'dev'
Requires-Dist: pybase64<=1.4.3,>=1.4; extra == 'dev'
Requires-Dist: pydantic<=2.12.5,>=2.10; extra == 'dev'
Requires-Dist: pytest; extra == 'dev'
Requires-Dist: pytest-cov; extra == 'dev'
Requires-Dist: pytest-mock; extra == 'dev'
Requires-Dist: requests<=2.32.5,>=2.32.4; extra == 'dev'
Requires-Dist: sphinx; extra == 'dev'
Requires-Dist: sphinx-autodoc-typehints; extra == 'dev'
Requires-Dist: sphinx-click; extra == 'dev'
Requires-Dist: sphinx-copybutton; extra == 'dev'
Requires-Dist: sphinx-design; extra == 'dev'
Requires-Dist: sphinxext-opengraph; extra == 'dev'
Requires-Dist: typeguard; extra == 'dev'
Requires-Dist: typer<=0.21.0,>=0.15; extra == 'dev'
Requires-Dist: uvicorn<=0.40.0,>=0.34; extra == 'dev'
Provides-Extra: docs
Requires-Dist: autodoc-pydantic; extra == 'docs'
Requires-Dist: click<=8.3.1,>=8.1; extra == 'docs'
Requires-Dist: debugpy<=1.8.19,>=1.8.14; extra == 'docs'
Requires-Dist: fastapi<=0.128.0,>=0.115; extra == 'docs'
Requires-Dist: fsspec[http,s3]<=2025.12.0,>=2024.12; extra == 'docs'
Requires-Dist: furo; extra == 'docs'
Requires-Dist: mlflow-skinny<=3.8.1,>=3.7.0; extra == 'docs'
Requires-Dist: myst-nb; extra == 'docs'
Requires-Dist: numpy<=2.4.0,>=1.26; extra == 'docs'
Requires-Dist: pybase64<=1.4.3,>=1.4; extra == 'docs'
Requires-Dist: pydantic<=2.12.5,>=2.10; extra == 'docs'
Requires-Dist: requests<=2.32.5,>=2.32.4; extra == 'docs'
Requires-Dist: sphinx; extra == 'docs'
Requires-Dist: sphinx-autodoc-typehints; extra == 'docs'
Requires-Dist: sphinx-click; extra == 'docs'
Requires-Dist: sphinx-copybutton; extra == 'docs'
Requires-Dist: sphinx-design; extra == 'docs'
Requires-Dist: sphinxext-opengraph; extra == 'docs'
Requires-Dist: typer<=0.21.0,>=0.15; extra == 'docs'
Requires-Dist: uvicorn<=0.40.0,>=0.34; extra == 'docs'
Provides-Extra: runtime
Requires-Dist: click<=8.3.1,>=8.1; extra == 'runtime'
Requires-Dist: debugpy<=1.8.19,>=1.8.14; extra == 'runtime'
Requires-Dist: fastapi<=0.128.0,>=0.115; extra == 'runtime'
Requires-Dist: fsspec[http,s3]<=2025.12.0,>=2024.12; extra == 'runtime'
Requires-Dist: mlflow-skinny<=3.8.1,>=3.7.0; extra == 'runtime'
Requires-Dist: numpy<=2.4.0,>=1.26; extra == 'runtime'
Requires-Dist: pybase64<=1.4.3,>=1.4; extra == 'runtime'
Requires-Dist: pydantic<=2.12.5,>=2.10; extra == 'runtime'
Requires-Dist: requests<=2.32.5,>=2.32.4; extra == 'runtime'
Requires-Dist: typer<=0.21.0,>=0.15; extra == 'runtime'
Requires-Dist: uvicorn<=0.40.0,>=0.34; extra == 'runtime'
